{
  "source": "Yahoo Finance chart API",
  "updatedAt": "2026-04-22T03:55:13.143306+00:00",
  "feeds": [
    {
      "sym": "WTI",
      "name": "WTI \u00b7 Texas",
      "venue": "NYMEX",
      "unit": "USD/bbl",
      "sourceSymbol": "CL=F",
      "last": 89.23,
      "previousClose": 89.67,
      "change": -0.44,
      "pct": -0.49,
      "history": [
        89.29,
        89.46,
        89.24,
        89.31,
        89.23,
        89.34,
        89.39,
        89.4,
        89.33,
        89.26,
        89.31,
        89.6,
        89.44,
        89.42,
        89.38,
        89.35,
        89.49,
        89.26,
        89.26,
        89.23
      ],
      "asOf": 1776829510
    },
    {
      "sym": "BRENT",
      "name": "Brent Crude",
      "venue": "ICE",
      "unit": "USD/bbl",
      "sourceSymbol": "BZ=F",
      "last": 92.9,
      "previousClose": 93.24,
      "change": -0.34,
      "pct": -0.36,
      "history": [
        92.83,
        92.85,
        92.89,
        92.9,
        92.85,
        92.86,
        92.94,
        92.88,
        92.83,
        92.79,
        92.85,
        92.95,
        92.94,
        92.76,
        92.69,
        93.11,
        92.99,
        92.95,
        92.96,
        92.9
      ],
      "asOf": 1776828957
    }
  ]
}
