{
  "source": "Yahoo Finance chart API",
  "updatedAt": "2026-04-28T01:55:18.719748+00:00",
  "feeds": [
    {
      "sym": "WTI",
      "name": "WTI \u00b7 Texas",
      "venue": "NYMEX",
      "unit": "USD/bbl",
      "sourceSymbol": "CL=F",
      "last": 96.88,
      "previousClose": 96.37,
      "change": 0.51,
      "pct": 0.53,
      "history": [
        96.6,
        96.63,
        96.92,
        97.07,
        96.99,
        97.05,
        97.0,
        96.98,
        97.03,
        97.31,
        97.17,
        97.2,
        97.18,
        97.2,
        97.07,
        97.09,
        96.95,
        96.89,
        96.92,
        96.88
      ],
      "asOf": 1777340712
    },
    {
      "sym": "BRENT",
      "name": "Brent Crude",
      "venue": "ICE",
      "unit": "USD/bbl",
      "sourceSymbol": "BZ=F",
      "last": 102.1,
      "previousClose": 101.69,
      "change": 0.41,
      "pct": 0.4,
      "history": [
        101.79,
        101.9,
        101.91,
        102.21,
        102.34,
        102.26,
        102.36,
        102.36,
        102.29,
        102.34,
        102.48,
        102.39,
        102.42,
        102.44,
        102.38,
        102.25,
        102.28,
        102.12,
        102.1,
        102.1
      ],
      "asOf": 1777340559
    }
  ]
}
